[
    {
        "ALCALDIA": "AZCAPOTZALCO",
        "COLONIA": "INFONAVIT EL ROSARIO",
        "CP": 2125,
        "ESTATUS": "HABILITADO",
        "SENTIDO": "N-S",
        "UBICACIÓN": "AV. CULTURA NORTE Y AV. DE LAS CULTURAS.",
        "VÍA PRINCIPAL": "AQUILES SERDÁN"
    },
    {
        "ALCALDIA": "AZCAPOTZALCO",
        "COLONIA": "INFONAVIT EL ROSARIO",
        "CP": 2120,
        "ESTATUS": "HABILITADO",
        "SENTIDO": "O-P",
        "UBICACIÓN": "AV. DE LAS CULTURAS Y CALLE MERCADERES.",
        "VÍA PRINCIPAL": "AQUILES SERDÁN"
    },
    {
        "ALCALDIA": "AZCAPOTZALCO",
        "COLONIA": "INFONAVIT EL ROSARIO",
        "CP": 2100,
        "ESTATUS": "HABILITADO",
        "SENTIDO": "O-P",
        "UBICACIÓN": "AV. AQUILES SERDÁN - ESQ. CALLE RÍO BLANCO.",
        "VÍA PRINCIPAL": "AQUILES SERDÁN"
    },
    {
        "ALCALDIA": "AZCAPOTZALCO",
        "COLONIA": "ANGEL ZIMBRON",
        "CP": 2099,
        "ESTATUS": "HABILITADO",
        "SENTIDO": "P-O",
        "UBICACIÓN": "AV. INVIERNO - ESQ. AV. AQUILES SERDÁN.",
        "VÍA PRINCIPAL": "AQUILES SERDÁN"
    },
    {
        "ALCALDIA": "AZCAPOTZALCO",
        "COLONIA": "SANTA BARBARA",
        "CP": 2110,
        "ESTATUS": "HABILITADO",
        "SENTIDO": "O-P",
        "UBICACIÓN": "EJE 5 NORTE AV. DEPORTIVO REYNOSA - AV. DE LAS GRANJAS.    - DEPÓSITO DE PEPSI",
        "VÍA PRINCIPAL": "EJE 5 NORTE"
    },
    {
        "ALCALDIA": "AZCAPOTZALCO",
        "COLONIA": "PASTEROS",
        "CP": 2150,
        "ESTATUS": "HABILITADO",
        "SENTIDO": "O-P",
        "UBICACIÓN": "AV. AQUILES SERDÁN - PASANDO  CALLE PRIVADA 16 DE SEPTIEMBRE.  -",
        "VÍA PRINCIPAL": "AQUILES SERDÁN"
    },
    {
        "ALCALDIA": "AZCAPOTZALCO",
        "COLONIA": "PEMEX PRADOS DEL ROSARIO",
        "CP": 2410,
        "ESTATUS": "HABILITADO",
        "SENTIDO": "P-O",
        "UBICACIÓN": "AV. HACIENDA EL ROSARIO Y AV. HACIENDA DE SOTELO ( MANUEL SALAZAR )  - ACCESO AL PARQUE TEZOZOMOC",
        "VÍA PRINCIPAL": "AQUILES SERDÁN"
    },
    {
        "ALCALDIA": "AZCAPOTZALCO",
        "COLONIA": "BARRIO NEXTENGO",
        "CP": 2730,
        "ESTATUS": "HABILITADO",
        "SENTIDO": "P-O",
        "UBICACIÓN": "EJE 3 NORTE SANTA APOLONIA - ESQ. AV. AQUILES SERDÁN.  - METRO CAMARONES",
        "VÍA PRINCIPAL": "AQUILES SERDÁN"
    },
    {
        "ALCALDIA": "AZCAPOTZALCO",
        "COLONIA": "NUEVA AMPL EL ROSARIO",
        "CP": 2220,
        "ESTATUS": "HABILITADO",
        "SENTIDO": "N-S",
        "UBICACIÓN": "EJE 5 NORTE AV. DEPORTIVO REYNOSA - ESQ.  AV. FERROCARRIL CENTRAL.",
        "VÍA PRINCIPAL": "EJE 5 NORTE"
    },
    {
        "ALCALDIA": "AZCAPOTZALCO",
        "COLONIA": "LOTERIA NACIONAL",
        "CP": 2080,
        "ESTATUS": "HABILITADO",
        "SENTIDO": "P-O",
        "UBICACIÓN": "EJE 3 NORTE CALZ. CAMARONES - ESQ. AV. HELIOPOLIS.",
        "VÍA PRINCIPAL": "CALZ. CAMARONES"
    },
    {
        "ALCALDIA": "AZCAPOTZALCO",
        "COLONIA": "SAN SALVADOR XOCHIMANCA",
        "CP": 2870,
        "ESTATUS": "HABILITADO",
        "SENTIDO": "P-O",
        "UBICACIÓN": "EJE 3 NORTE CALZ. CAMARONES - PASANDO AV. BIÓLOGO MAXIMINO MARTÍNEZ.",
        "VÍA PRINCIPAL": "CALZ. CAMARONES"
    },
    {
        "ALCALDIA": "AZCAPOTZALCO",
        "COLONIA": "LOTERIA NACIONAL",
        "CP": 2070,
        "ESTATUS": "HABILITADO",
        "SENTIDO": "P-O",
        "UBICACIÓN": "EJE 3 NORTE CALZ. CAMARONES - ESQ. NORTE 87 B",
        "VÍA PRINCIPAL": "CALZ. CAMARONES"
    },
    {
        "ALCALDIA": "AZCAPOTZALCO",
        "COLONIA": "OBRERO POPULAR",
        "CP": 2840,
        "ESTATUS": "HABILITADO",
        "SENTIDO": "P-O",
        "UBICACIÓN": "EJE 3 NORTE CALZ. CAMARONES - ESQ. CALLE NORTE 67.",
        "VÍA PRINCIPAL": "CALZ. CAMARONES"
    }
]