[
    {
        "ALCALDIA": "CUAUHTEMOC",
        "COLONIA": "JUAREZ",
        "CP": 6600.0,
        "ESTATUS": "HABILITADO",
        "SENTIDO": "N-S",
        "UBICACIÓN": "CALLE VERSALLES Y ATENAS  (HOTEL FIESTA AMERICANA)",
        "VÍA PRINCIPAL": "REFORMA (COLÓN-PERIFÉRICO)"
    },
    {
        "ALCALDIA": "CUAUHTEMOC",
        "COLONIA": "CENTRO",
        "CP": 5010.0,
        "ESTATUS": "HABILITADO",
        "SENTIDO": "P-O",
        "UBICACIÓN": "CALLE AYUNTAMIENTO Y DOLORES",
        "VÍA PRINCIPAL": "REFORMA (COLÓN-PERIFÉRICO)"
    },
    {
        "ALCALDIA": "CUAUHTEMOC",
        "COLONIA": "CENTRO",
        "CP": 6600.0,
        "ESTATUS": "HABILITADO",
        "SENTIDO": "S-N",
        "UBICACIÓN": "CALLE EMILIO  Y ENRICO MTZ (CIUDADELA)",
        "VÍA PRINCIPAL": "REFORMA (COLÓN-PERIFÉRICO)"
    },
    {
        "ALCALDIA": "CUAUHTEMOC",
        "COLONIA": "OBRERA",
        "CP": 6800.0,
        "ESTATUS": "HABILITADO",
        "SENTIDO": "N-S",
        "UBICACIÓN": "CALZADA DE TLALPAN Y EJE 3 SUR PEÓN CONTRERAS (PUENTE EJE 3)",
        "VÍA PRINCIPAL": "TLALPAN"
    },
    {
        "ALCALDIA": "CUAUHTEMOC",
        "COLONIA": "OBRERA",
        "CP": 6800.0,
        "ESTATUS": "HABILITADO",
        "SENTIDO": "N-S",
        "UBICACIÓN": "CALZ. SAN ANTONIO ABAD - ESQ. CALLE RAFAEL DELGADO",
        "VÍA PRINCIPAL": "TLALPAN"
    },
    {
        "ALCALDIA": "CUAUHTEMOC",
        "COLONIA": "OBRERA",
        "CP": 6860.0,
        "ESTATUS": "HABILITADO",
        "SENTIDO": "S-N",
        "UBICACIÓN": "CALZ. SAN ANTONIO ABAD - ESQ. CALZ. CHABACANO",
        "VÍA PRINCIPAL": "TLALPAN"
    },
    {
        "ALCALDIA": "CUAUHTEMOC",
        "COLONIA": "JUAREZ",
        "CP": 6600.0,
        "ESTATUS": "HABILITADO",
        "SENTIDO": "N-S",
        "UBICACIÓN": "NIZA ESQ. LIVERPOOL (ENTRE AV. CHAPULTEPEC E INSURGENTES",
        "VÍA PRINCIPAL": "INSURGENTES (SUR)"
    },
    {
        "ALCALDIA": "CUAUHTEMOC",
        "COLONIA": "ROMA SUR",
        "CP": 6170.0,
        "ESTATUS": "HABILITADO",
        "SENTIDO": "N-S",
        "UBICACIÓN": "AVENIDA INSURGENTES SUR Y CALLE TEOTIHUACÁN",
        "VÍA PRINCIPAL": "INSURGENTES (SUR)"
    },
    {
        "ALCALDIA": "CUAUHTEMOC",
        "COLONIA": "ROMA NORTE",
        "CP": 6760.0,
        "ESTATUS": "HABILITADO",
        "SENTIDO": "N-S",
        "UBICACIÓN": "AVENIDA INSURGENTES SUR - PASANDO DURANGO",
        "VÍA PRINCIPAL": "INSURGENTES (SUR)"
    },
    {
        "ALCALDIA": "CUAUHTEMOC",
        "COLONIA": "INHAB",
        "CP": 6400.0,
        "ESTATUS": "HABILITADO",
        "SENTIDO": "N-S",
        "UBICACIÓN": "AV. INSURGENTES NORTE Y ESQ. CALLE SALVADOR DÍAZ MIRÓN",
        "VÍA PRINCIPAL": "INSURGENTES (NORTE)"
    },
    {
        "ALCALDIA": "CUAUHTEMOC",
        "COLONIA": "TABACALERA",
        "CP": 6030.0,
        "ESTATUS": "HABILITADO",
        "SENTIDO": "S-N",
        "UBICACIÓN": "AV. INSURGENTES CENTRO Y CALLE EDISON",
        "VÍA PRINCIPAL": "INSURGENTES (NORTE)"
    },
    {
        "ALCALDIA": "CUAUHTEMOC",
        "COLONIA": "HIPODROMO",
        "CP": 6170.0,
        "ESTATUS": "HABILITADO",
        "SENTIDO": "N-S",
        "UBICACIÓN": "AV. INSURGENTES SUR - PASANDO TEHUANTEPEC",
        "VÍA PRINCIPAL": "INSURGENTES (SUR)"
    },
    {
        "ALCALDIA": "CUAUHTEMOC",
        "COLONIA": "DOCTORES",
        "CP": 6800.0,
        "ESTATUS": "HABILITADO",
        "SENTIDO": "S-N",
        "UBICACIÓN": "EJE CENTRAL LÁZARO CÁRDENAS Y CALLE EFRÉN REBOLLEDO",
        "VÍA PRINCIPAL": "EJE CENTRAL"
    },
    {
        "ALCALDIA": "CUAUHTEMOC",
        "COLONIA": "OBRERA",
        "CP": 6800.0,
        "ESTATUS": "HABILITADO",
        "SENTIDO": "S-N",
        "UBICACIÓN": "EJE CENTRAL AV. LÁZARO CÁRDENAS - PASANDO ANTONIO SOLIS",
        "VÍA PRINCIPAL": "EJE CENTRAL"
    },
    {
        "ALCALDIA": "CUAUHTEMOC",
        "COLONIA": "OBRERA",
        "CP": 6720.0,
        "ESTATUS": "HABILITADO",
        "SENTIDO": "S-N",
        "UBICACIÓN": "EJE CENTRAL AV. LÁZARO CÁRDENAS - ESQ. CALLE FRAY JUAN DE TORQUEMADA",
        "VÍA PRINCIPAL": "EJE CENTRAL"
    },
    {
        "ALCALDIA": "CUAUHTEMOC",
        "COLONIA": "OBRERA",
        "CP": 6800.0,
        "ESTATUS": "HABILITADO",
        "SENTIDO": "S-N",
        "UBICACIÓN": "EJE CENTRAL AV. LÁZARO CÁRDENAS - ESQ. CALLE MANUEL M. FLORES",
        "VÍA PRINCIPAL": "EJE CENTRAL"
    },
    {
        "ALCALDIA": "CUAUHTEMOC",
        "COLONIA": "DOCTORES",
        "CP": 6800.0,
        "ESTATUS": "HABILITADO",
        "SENTIDO": "S-N",
        "UBICACIÓN": "EJE CENTRAL AV. LÁZARO CÁRDENAS - PASANDO JUAN A. MATEOS",
        "VÍA PRINCIPAL": "EJE CENTRAL"
    },
    {
        "ALCALDIA": "CUAUHTEMOC",
        "COLONIA": "HIPODROMO DE LA CONDESA",
        "CP": 6170.0,
        "ESTATUS": "HABILITADO",
        "SENTIDO": "O-P",
        "UBICACIÓN": "CIRCUITO INTERIOR DIAGONAL PATRIOTISMO Y CALLE CHOAPAN",
        "VÍA PRINCIPAL": "PATRIOTISMO"
    },
    {
        "ALCALDIA": "CUAUHTEMOC",
        "COLONIA": "HIPODROMO DE LA CONDESA",
        "CP": 6170.0,
        "ESTATUS": "HABILITADO",
        "SENTIDO": "P-O",
        "UBICACIÓN": "AV. TAMAULIPAS Y BENAJAMIN HILL (HIPÓDROMO CONDESA)",
        "VÍA PRINCIPAL": "PATRIOTISMO"
    },
    {
        "ALCALDIA": "CUAUHTEMOC",
        "COLONIA": "HIPODROMO",
        "CP": 6170.0,
        "ESTATUS": "HABILITADO/DIGITAL",
        "SENTIDO": "P-O",
        "UBICACIÓN": "AV. NUEVO LEON Y CAMPECHE",
        "VÍA PRINCIPAL": "CONDESA-ROMA"
    },
    {
        "ALCALDIA": "CUAUHTEMOC",
        "COLONIA": "HIPODROMO",
        "CP": 6170.0,
        "ESTATUS": "HABILITADO",
        "SENTIDO": "P-O",
        "UBICACIÓN": "AV. NUEVO LEON Y CAMPECHE",
        "VÍA PRINCIPAL": "CONDESA-ROMA"
    },
    {
        "ALCALDIA": "CUAUHTEMOC",
        "COLONIA": "ESCANDON",
        "CP": 11800.0,
        "ESTATUS": "HABILITADO",
        "SENTIDO": "P-O",
        "UBICACIÓN": "AV. NUEVO LEON  Y VIADUCTO",
        "VÍA PRINCIPAL": "CONDESA-ROMA"
    },
    {
        "ALCALDIA": "CUAUHTEMOC",
        "COLONIA": "ESCANDON",
        "CP": 11800.0,
        "ESTATUS": "HABILITADO/DIGITAL",
        "SENTIDO": "P-O",
        "UBICACIÓN": "AV. NUEVO LEON  Y VIADUCTO",
        "VÍA PRINCIPAL": "CONDESA-ROMA"
    },
    {
        "ALCALDIA": "CUAUHTEMOC",
        "COLONIA": "DOCTORES",
        "CP": 6720.0,
        "ESTATUS": "HABILITADO",
        "SENTIDO": "P-O",
        "UBICACIÓN": "AVENIDA DOCTOR RÍO DE LA LOZA - PASANDO AV. DOCTOR JOSÉ MARÍA VÉRTIZ",
        "VÍA PRINCIPAL": "AV. CHAPULTEPEC"
    },
    {
        "ALCALDIA": "CUAUHTEMOC",
        "COLONIA": "CENTRO",
        "CP": 6800.0,
        "ESTATUS": "HABILITADO",
        "SENTIDO": "P-O",
        "UBICACIÓN": "AV. FRAY SERVANDO TERESA DE MIER - PASANDO AV. BOLIVAR",
        "VÍA PRINCIPAL": "FRAY SERVANDO"
    },
    {
        "ALCALDIA": "CUAUHTEMOC",
        "COLONIA": "DOCTORES",
        "CP": 6720.0,
        "ESTATUS": "HABILITADO",
        "SENTIDO": "P-O",
        "UBICACIÓN": "AV. DOCTOR RÍO DE LA LOZA - ESQ. CALLE DR. VALENZUELA",
        "VÍA PRINCIPAL": "AV. CHAPULTEPEC"
    },
    {
        "ALCALDIA": "CUAUHTEMOC",
        "COLONIA": "DOCTORES",
        "CP": 6720.0,
        "ESTATUS": "HABILITADO",
        "SENTIDO": "P-O",
        "UBICACIÓN": "AV. DOCTOR RÍO DE LA LOZA - PASANDO AV. CHAPULTEPEC",
        "VÍA PRINCIPAL": "AV. CHAPULTEPEC"
    },
    {
        "ALCALDIA": "CUAUHTEMOC",
        "COLONIA": "ASTURIAS",
        "CP": 6850.0,
        "ESTATUS": "HABILITADO",
        "SENTIDO": "O-P",
        "UBICACIÓN": "AV. VIADUCTO RÍO DE LA PIEDAD - PASANDO EJE 1 OTE. AV. ANDRÉS MOLINA ENRÍQUEZ",
        "VÍA PRINCIPAL": "FRAY SERVANDO"
    },
    {
        "ALCALDIA": "CUAUHTEMOC",
        "COLONIA": "DOCTORES",
        "CP": 6700.0,
        "ESTATUS": "HABILITADO",
        "SENTIDO": "N-S",
        "UBICACIÓN": "EJE 1 PONIENTE AVENIDA CUAUHTÉMOC - CALLE SAN LUIS POTOSÍ",
        "VÍA PRINCIPAL": "AV. CUAUHTÉMOC"
    },
    {
        "ALCALDIA": "CUAUHTEMOC",
        "COLONIA": "ROMA NORTE",
        "CP": 6700.0,
        "ESTATUS": "HABILITADO",
        "SENTIDO": "P-O",
        "UBICACIÓN": "EJE 2 SUR AV. QUERÉTARO - ESQ. EJE 1 PONIENTE AV. CUAUHTÉMOC - GASOLINERIA",
        "VÍA PRINCIPAL": "AV. CUAUHTÉMOC"
    },
    {
        "ALCALDIA": "CUAUHTEMOC",
        "COLONIA": "CONDESA",
        "CP": 6760.0,
        "ESTATUS": "HABILITADO",
        "SENTIDO": "P-O",
        "UBICACIÓN": "CALLE SONORA Y PARQUE ESPAÑA",
        "VÍA PRINCIPAL": "CONDESA-ROMA"
    },
    {
        "ALCALDIA": "CUAUHTEMOC",
        "COLONIA": "CENTRO URBANO BENITO JUAREZ",
        "CP": 6760.0,
        "ESTATUS": "HABILITADO",
        "SENTIDO": "N-S",
        "UBICACIÓN": "ORIZABA PASANDO ANTONIO M. ANZA",
        "VÍA PRINCIPAL": "CONDESA-ROMA"
    },
    {
        "ALCALDIA": "CUAUHTEMOC",
        "COLONIA": "ROMA NORTE",
        "CP": 6700.0,
        "ESTATUS": "HABILITADO",
        "SENTIDO": "P-O",
        "UBICACIÓN": "AV. YUCATÁN ENTRE JALAPA Y PROL. ORIZABA",
        "VÍA PRINCIPAL": "CONDESA-ROMA"
    },
    {
        "ALCALDIA": "CUAUHTEMOC",
        "COLONIA": "ROMA NORTE",
        "CP": 6760.0,
        "ESTATUS": "HABILITADO",
        "SENTIDO": "S-N",
        "UBICACIÓN": "CALLE ORIZABA - ESQ. CALLE ZACATECAS.",
        "VÍA PRINCIPAL": "CONDESA-ROMA"
    },
    {
        "ALCALDIA": "CUAUHTEMOC",
        "COLONIA": "ROMA NORTE",
        "CP": 6760.0,
        "ESTATUS": "HABILITADO/DIGITAL",
        "SENTIDO": "S-N",
        "UBICACIÓN": "CALLE ORIZABA - ESQ. CALLE ZACATECAS.",
        "VÍA PRINCIPAL": "CONDESA-ROMA"
    },
    {
        "ALCALDIA": "CUAUHTEMOC",
        "COLONIA": "CUAUHTEMOC",
        "CP": 6500.0,
        "ESTATUS": "HABILITADO",
        "SENTIDO": "S-N",
        "UBICACIÓN": "RIO TIBER ESQ RIO LERMA",
        "VÍA PRINCIPAL": "MONTERREY"
    },
    {
        "ALCALDIA": "CUAUHTEMOC",
        "COLONIA": "CUAUHTEMOC",
        "CP": 6500.0,
        "ESTATUS": "HABILITADO",
        "SENTIDO": "P-O",
        "UBICACIÓN": "AVENIDA PARQUE VÍA Y CALLE RÍO AMOY (TELMEX)",
        "VÍA PRINCIPAL": "PARQUE VIA"
    },
    {
        "ALCALDIA": "CUAUHTEMOC",
        "COLONIA": "ROMA NORTE",
        "CP": 6760.0,
        "ESTATUS": "HABILITADO",
        "SENTIDO": "S-N",
        "UBICACIÓN": "EJE 2 PTE. MONTERREY ENTRE QUERÉTARO Y ZACATECAS",
        "VÍA PRINCIPAL": "MONTERREY"
    },
    {
        "ALCALDIA": "CUAUHTEMOC",
        "COLONIA": "ROMA SUR",
        "CP": 6760.0,
        "ESTATUS": "HABILITADO/DIGITAL",
        "SENTIDO": "O-P",
        "UBICACIÓN": "VIADUCTO AV. PRESIDENTE MIGUEL ALEMÁN - ESQ. EJE 2 PONIENTE AV. MONTERREY.",
        "VÍA PRINCIPAL": "MONTERREY"
    },
    {
        "ALCALDIA": "CUAUHTEMOC",
        "COLONIA": "ROMA SUR",
        "CP": 6760.0,
        "ESTATUS": "HABILITADO",
        "SENTIDO": "O-P",
        "UBICACIÓN": "VIADUCTO AV. PRESIDENTE MIGUEL ALEMÁN - ESQ. EJE 2 PONIENTE AV. MONTERREY.",
        "VÍA PRINCIPAL": "MONTERREY"
    },
    {
        "ALCALDIA": "CUAUHTEMOC",
        "COLONIA": "ROMA SUR",
        "CP": 6760.0,
        "ESTATUS": "HABILITADO",
        "SENTIDO": "O-P",
        "UBICACIÓN": "AVENIDA VIADUCTO PRESIDENTE MIGUEL ALEMÁN - CALLE IGUALA",
        "VÍA PRINCIPAL": "AV. COYOACAN"
    },
    {
        "ALCALDIA": "CUAUHTEMOC",
        "COLONIA": "SAN MIGUEL CHAPULTEPEC",
        "CP": 11850.0,
        "ESTATUS": "HABILITADO",
        "SENTIDO": "O-P",
        "UBICACIÓN": "AVENIDA DIAGONAL PATRIOTISMO Y CIRCUITO INTERIOR MASTRO JOSÉ VASCONCELOS",
        "VÍA PRINCIPAL": "CIRCUITO INTERIOR"
    },
    {
        "ALCALDIA": "CUAUHTEMOC",
        "COLONIA": "CONDESA",
        "CP": "#N/A",
        "ESTATUS": "HABILITADO",
        "SENTIDO": "S-N",
        "UBICACIÓN": "CIRCUITO INTERIOR AVENIDA MAESTRO JOSÉ VASCONCELOS - CALLE AGUSTÍN MELGAR",
        "VÍA PRINCIPAL": "CIRCUITO INTERIOR"
    },
    {
        "ALCALDIA": "CUAUHTEMOC",
        "COLONIA": "AGRICULTURA",
        "CP": 6400.0,
        "ESTATUS": "HABILITADO",
        "SENTIDO": "S-N",
        "UBICACIÓN": "AV. INSTITUTO TÉCNICO INDUSTRIAL - PASANDO CALLE SOR JUANA INÉS DE LA CRUZ",
        "VÍA PRINCIPAL": "CIRCUITO INTERIOR"
    },
    {
        "ALCALDIA": "CUAUHTEMOC",
        "COLONIA": "SANTA MARIA LA RIBERA",
        "CP": 6400.0,
        "ESTATUS": "HABILITADO",
        "SENTIDO": "S-N",
        "UBICACIÓN": "INSTITUTO TÉCNICO INDUSTRIAL - PASANDO AV. RICARDO FLORES MAGÓN",
        "VÍA PRINCIPAL": "CIRCUITO INTERIOR"
    },
    {
        "ALCALDIA": "CUAUHTEMOC",
        "COLONIA": "ATLAMPA",
        "CP": 6400.0,
        "ESTATUS": "HABILITADO",
        "SENTIDO": "P-O",
        "UBICACIÓN": "AV. RICARDO FLORES MAGÓN - ESQ. SABINO",
        "VÍA PRINCIPAL": "CIRCUITO INTERIOR"
    },
    {
        "ALCALDIA": "CUAUHTEMOC",
        "COLONIA": "CONDESA",
        "CP": 6140.0,
        "ESTATUS": "HABILITADO",
        "SENTIDO": "S-N",
        "UBICACIÓN": "CIRCUITO INTERIOR AV. MAESTRO JOSÉ VASCONCELOS - PASANDO CALLE VICENTE SUÁREZ.",
        "VÍA PRINCIPAL": "CIRCUITO INTERIOR"
    },
    {
        "ALCALDIA": "CUAUHTEMOC",
        "COLONIA": "HIPODROMO",
        "CP": 6170.0,
        "ESTATUS": "HABILITADO",
        "SENTIDO": "O-P",
        "UBICACIÓN": "EJE 3 SUR BAJA CALIFORNIA Y CALLE SULTEPEC",
        "VÍA PRINCIPAL": "BENJAMÍN FRANKLIN"
    },
    {
        "ALCALDIA": "CUAUHTEMOC",
        "COLONIA": "ALGARIN",
        "CP": 6720.0,
        "ESTATUS": "HABILITADO",
        "SENTIDO": "O-P",
        "UBICACIÓN": "EJE CENTRAL LÁZARO CÁRDENAS Y EJE 3 SUR BAJA CALIFORNIA (METRO LÁZARO CÁRDENAS)",
        "VÍA PRINCIPAL": "AÑIL"
    },
    {
        "ALCALDIA": "CUAUHTEMOC",
        "COLONIA": "ROMA SUR",
        "CP": 6760.0,
        "ESTATUS": "HABILITADO",
        "SENTIDO": "O-P",
        "UBICACIÓN": "EJE 3 SUR AV. BAJA CALIFORNIA - ESQ. EJE 2 PONIENTE AV. MONTERREY.",
        "VÍA PRINCIPAL": "BENJAMÍN FRANKLIN"
    },
    {
        "ALCALDIA": "CUAUHTEMOC",
        "COLONIA": "SANTA MARIA LA RIBERA",
        "CP": 6400.0,
        "ESTATUS": "HABILITADO",
        "SENTIDO": "O-P",
        "UBICACIÓN": "AVENIDA RIBERA DE SAN COSME Y CALLE FRESNO",
        "VÍA PRINCIPAL": "MÉXICO TACUBA"
    },
    {
        "ALCALDIA": "CUAUHTEMOC",
        "COLONIA": "BUENAVISTA",
        "CP": 6350.0,
        "ESTATUS": "HABILITADO",
        "SENTIDO": "O-P",
        "UBICACIÓN": "AV. PUENTE DE ALVARADO - ESQ. BUENAVISTA",
        "VÍA PRINCIPAL": "MÉXICO TACUBA"
    }
]